anomalib/__init__.py
anomalib/py.typed
anomalib/callbacks/__init__.py
anomalib/callbacks/checkpoint.py
anomalib/callbacks/graph.py
anomalib/callbacks/model_loader.py
anomalib/callbacks/tiler_configuration.py
anomalib/callbacks/timer.py
anomalib/callbacks/visualizer.py
anomalib/callbacks/nncf/__init__.py
anomalib/callbacks/nncf/callback.py
anomalib/callbacks/nncf/utils.py
anomalib/cli/__init__.py
anomalib/cli/cli.py
anomalib/cli/install.py
anomalib/cli/pipelines.py
anomalib/cli/utils/__init__.py
anomalib/cli/utils/help_formatter.py
anomalib/cli/utils/installation.py
anomalib/cli/utils/openvino.py
anomalib/data/__init__.py
anomalib/data/errors.py
anomalib/data/predict.py
anomalib/data/dataclasses/__init__.py
anomalib/data/dataclasses/generic.py
anomalib/data/dataclasses/numpy/__init__.py
anomalib/data/dataclasses/numpy/base.py
anomalib/data/dataclasses/numpy/depth.py
anomalib/data/dataclasses/numpy/image.py
anomalib/data/dataclasses/numpy/video.py
anomalib/data/dataclasses/torch/__init__.py
anomalib/data/dataclasses/torch/base.py
anomalib/data/dataclasses/torch/depth.py
anomalib/data/dataclasses/torch/image.py
anomalib/data/dataclasses/torch/video.py
anomalib/data/datamodules/__init__.py
anomalib/data/datamodules/base/__init__.py
anomalib/data/datamodules/base/image.py
anomalib/data/datamodules/base/video.py
anomalib/data/datamodules/depth/__init__.py
anomalib/data/datamodules/depth/adam_3d.py
anomalib/data/datamodules/depth/folder_3d.py
anomalib/data/datamodules/depth/mvtec_3d.py
anomalib/data/datamodules/image/__init__.py
anomalib/data/datamodules/image/bmad.py
anomalib/data/datamodules/image/btech.py
anomalib/data/datamodules/image/datumaro.py
anomalib/data/datamodules/image/folder.py
anomalib/data/datamodules/image/kolektor.py
anomalib/data/datamodules/image/mpdd.py
anomalib/data/datamodules/image/mvtec_loco.py
anomalib/data/datamodules/image/mvtecad.py
anomalib/data/datamodules/image/mvtecad2.py
anomalib/data/datamodules/image/realiad.py
anomalib-2.2.0.dist-info/METADATA
anomalib-2.2.0.dist-info/WHEEL
anomalib-2.2.0.dist-info/entry_points.txt
anomalib-2.2.0.dist-info/licenses/LICENSE
anomalib-2.2.0.dist-info/RECORD
