Metadata-Version: 2.4
Name: anomalib
Version: 2.2.0
Summary: anomalib - Anomaly Detection Library
Author: Intel OpenVINO
License: 
License-File: LICENSE
Classifier: Development Status :: 5 - Production/Stable
Classifier: Intended Audience :: Developers
Classifier: License :: OSI Approved :: Apache Software License
Classifier: Programming Language :: Python
Classifier: Programming Language :: Python :: 3
Classifier: Programming Language :: Python :: 3.10
Classifier: Programming Language :: Python :: 3.11
Classifier: Programming Language :: Python :: 3.12
Classifier: Topic :: Scientific/Engineering :: Artificial Intelligence
Classifier: Topic :: Software Development :: Libraries
Requires-Python: >=3.10
Requires-Dist: docstring-parser
Requires-Dist: einops>=0.3.2
Requires-Dist: freia>=0.2
Requires-Dist: imagecodecs
Requires-Dist: jsonargparse[signatures]>=4.27.7
Requires-Dist: kornia>=0.6.6
Requires-Dist: lightning-utilities
Requires-Dist: lightning>=2.2
Requires-Dist: matplotlib>=3.4.3
Requires-Dist: omegaconf>=2.1.1
Requires-Dist: opencv-python>=4.5.3.56
Requires-Dist: pandas>=1.1.0
Requires-Dist: pillow>=10.1.0
Requires-Dist: rich-argparse
Requires-Dist: rich>=13.5.2
Requires-Dist: scikit-image
Requires-Dist: scikit-learn
Requires-Dist: tifffile
Requires-Dist: timm
Requires-Dist: torchmetrics>=1.8.2
Provides-Extra: clip
Requires-Dist: open-clip-torch<2.26.1,>=2.23.0; extra == 'clip'
Provides-Extra: cpu
Requires-Dist: torch>=2.4.0; extra == 'cpu'
Requires-Dist: torchvision>=0.19.0; extra == 'cpu'
Provides-Extra: cu118
Requires-Dist: torch>=2.4.0; extra == 'cu118'
Requires-Dist: torchvision>=0.19.0; extra == 'cu118'
Provides-Extra: cu121
Requires-Dist: torch>=2.4.0; extra == 'cu121'
Requires-Dist: torchvision>=0.19.0; extra == 'cu121'
Provides-Extra: cu124
Requires-Dist: torch>=2.4.0; extra == 'cu124'
Requires-Dist: torchvision>=0.19.0; extra == 'cu124'
Provides-Extra: dev
Requires-Dist: av>=10.0.0; extra == 'dev'
Requires-Dist: comet-ml>=3.31.7; extra == 'dev'
Requires-Dist: commitizen; extra == 'dev'
Requires-Dist: coverage[toml]; extra == 'dev'
Requires-Dist: gitpython; extra == 'dev'
Requires-Dist: gradio>=4; extra == 'dev'
Requires-Dist: ipykernel; extra == 'dev'
Requires-Dist: ipywidgets; extra == 'dev'
Requires-Dist: mlflow>=1.0.0; extra == 'dev'
Requires-Dist: myst-parser[linkify]; extra == 'dev'
Requires-Dist: nbsphinx; extra == 'dev'
Requires-Dist: nncf>=2.10.0; extra == 'dev'
Requires-Dist: notebook; extra == 'dev'
Requires-Dist: ollama>=0.4.0; extra == 'dev'
Requires-Dist: onnx>=1.16.0; extra == 'dev'
Requires-Dist: open-clip-torch<2.26.1,>=2.23.0; extra == 'dev'
Requires-Dist: openai; extra == 'dev'
Requires-Dist: openvino>=2024.0; extra == 'dev'
Requires-Dist: pandoc; extra == 'dev'
Requires-Dist: pre-commit; extra == 'dev'
Requires-Dist: pytest; extra == 'dev'
Requires-Dist: pytest-cov; extra == 'dev'
Requires-Dist: pytest-json-report; extra == 'dev'
Requires-Dist: pytest-mock; extra == 'dev'
Requires-Dist: pytest-sugar; extra == 'dev'
Requires-Dist: pytest-timeout; extra == 'dev'
Requires-Dist: pytest-xdist; extra == 'dev'
Requires-Dist: python-dotenv; extra == 'dev'
Requires-Dist: sphinx; extra == 'dev'
Requires-Dist: sphinx-autodoc-typehints; extra == 'dev'
Requires-Dist: sphinx-book-theme; extra == 'dev'
Requires-Dist: sphinx-copybutton; extra == 'dev'
Requires-Dist: sphinx-design; extra == 'dev'
Requires-Dist: tensorboard; extra == 'dev'
Requires-Dist: tox; extra == 'dev'
Requires-Dist: transformers; extra == 'dev'
Requires-Dist: wandb; extra == 'dev'
Provides-Extra: docs
Requires-Dist: myst-parser[linkify]; extra == 'docs'
Requires-Dist: nbsphinx; extra == 'docs'
Requires-Dist: pandoc; extra == 'docs'
Requires-Dist: sphinx; extra == 'docs'
Requires-Dist: sphinx-autodoc-typehints; extra == 'docs'
Requires-Dist: sphinx-book-theme; extra == 'docs'
Requires-Dist: sphinx-copybutton; extra == 'docs'
Requires-Dist: sphinx-design; extra == 'docs'
Provides-Extra: full
Requires-Dist: av>=10.0.0; extra == 'full'
Requires-Dist: comet-ml>=3.31.7; extra == 'full'
Requires-Dist: gitpython; extra == 'full'
Requires-Dist: gradio>=4; extra == 'full'
Requires-Dist: ipykernel; extra == 'full'
Requires-Dist: ipywidgets; extra == 'full'
Requires-Dist: mlflow>=1.0.0; extra == 'full'
Requires-Dist: nncf>=2.10.0; extra == 'full'
Requires-Dist: notebook; extra == 'full'
Requires-Dist: ollama>=0.4.0; extra == 'full'
Requires-Dist: onnx>=1.16.0; extra == 'full'
Requires-Dist: open-clip-torch<2.26.1,>=2.23.0; extra == 'full'
Requires-Dist: openai; extra == 'full'
Requires-Dist: openvino>=2024.0; extra == 'full'
Requires-Dist: python-dotenv; extra == 'full'
Requires-Dist: tensorboard; extra == 'full'
Requires-Dist: transformers; extra == 'full'
Requires-Dist: wandb; extra == 'full'
Provides-Extra: loggers
Requires-Dist: comet-ml>=3.31.7; extra == 'loggers'
Requires-Dist: gradio>=4; extra == 'loggers'
Requires-Dist: mlflow>=1.0.0; extra == 'loggers'
Requires-Dist: tensorboard; extra == 'loggers'
Requires-Dist: wandb; extra == 'loggers'
Provides-Extra: notebooks
Requires-Dist: gitpython; extra == 'notebooks'
Requires-Dist: ipykernel; extra == 'notebooks'
Requires-Dist: ipywidgets; extra == 'notebooks'
Requires-Dist: notebook; extra == 'notebooks'
Provides-Extra: openvino
Requires-Dist: nncf>=2.10.0; extra == 'openvino'
Requires-Dist: onnx>=1.16.0; extra == 'openvino'
Requires-Dist: openvino>=2024.0; extra == 'openvino'
Provides-Extra: rocm
Requires-Dist: pytorch-triton-rocm; (sys_platform == 'linux') and extra == 'rocm'
Requires-Dist: torch>=2.4.0; extra == 'rocm'
Requires-Dist: torchvision>=0.19.0; extra == 'rocm'
Provides-Extra: test
Requires-Dist: commitizen; extra == 'test'
Requires-Dist: coverage[toml]; extra == 'test'
Requires-Dist: pre-commit; extra == 'test'
Requires-Dist: pytest; extra == 'test'
Requires-Dist: pytest-cov; extra == 'test'
Requires-Dist: pytest-json-report; extra == 'test'
Requires-Dist: pytest-mock; extra == 'test'
Requires-Dist: pytest-sugar; extra == 'test'
Requires-Dist: pytest-timeout; extra == 'test'
Requires-Dist: pytest-xdist; extra == 'test'
Requires-Dist: tox; extra == 'test'
Provides-Extra: video
Requires-Dist: av>=10.0.0; extra == 'video'
Provides-Extra: vlm
Requires-Dist: ollama>=0.4.0; extra == 'vlm'
Requires-Dist: openai; extra == 'vlm'
Requires-Dist: python-dotenv; extra == 'vlm'
Requires-Dist: transformers; extra == 'vlm'
Provides-Extra: xpu
Requires-Dist: pytorch-triton-xpu; (sys_platform == 'linux' or sys_platform == 'win32') and extra == 'xpu'
Requires-Dist: torch>=2.4.0; extra == 'xpu'
Requires-Dist: torchvision>=0.19.0; extra == 'xpu'
